README
setup.py
sphinx/__init__.py
sphinx.webtools.egg-info/PKG-INFO
sphinx.webtools.egg-info/SOURCES.txt
sphinx.webtools.egg-info/dependency_links.txt
sphinx.webtools.egg-info/namespace_packages.txt
sphinx.webtools.egg-info/requires.txt
sphinx.webtools.egg-info/top_level.txt
sphinx/webtools/__init__.py
sphinx/webtools/pickler_tools.py
sphinx/webtools/search_tools.py