Metadata-Version: 1.0
Name: sphinx.webtools
Version: 0.2.2
Summary: Sphinx web tools for python web frameworks
Home-page: http://bitbucket.org/florent/sphinx-webtools
Author: Florent PIGOUT
Author-email: florent.pigout@gmail.com
License: BSD
Platform: UNKNOWN
